demo_app/__init__.py
demo_app/hooks/__init__.py
demo_app/hooks/issuer.py
demo_app/lib/__init__.py
demo_app/lib/issuer.py
demo_app/routes/__init__.py
demo_app/routes/demo.py
demo_app/routes/issuer.py
demo_app/routes/nats.py
demo_app/settings.py
demo_app/spec.py
wire/__init__.py
wire/__main__.py
wire/cli/__init__.py
wire/core/__init__.py
wire/core/container.py
wire/core/dependencies.py
wire/core/settings.py
wire/core/spec.py
wire/core/tasks.py
wire/core/utils.py
wire/providers/__init__.py
wire/providers/cors.py
wire/providers/debug/__init__.py
wire/providers/debug/router.py
wire/providers/logger/__init__.py
wire/providers/logger/structlog/__init__.py
wire/providers/logger/structlog/_log_levels.py
wire/providers/metrics/__init__.py
wire/providers/metrics/prometheus.py
wire/providers/oidc/__init__.py
wire/providers/oidc/errors.py
wire/providers/oidc/models.py
wire/providers/oidc/provider.py
wire/providers/tracing/__init__.py
wire/providers/tracing/opentelemetry.py
fastapi_wire-0.0.1a4.dist-info/entry_points.txt
fastapi_wire-0.0.1a4.dist-info/WHEEL
fastapi_wire-0.0.1a4.dist-info/METADATA
fastapi_wire-0.0.1a4.dist-info/RECORD
