Metadata-Version: 2.1
Name: fastapi-wire
Version: 0.0.1a4
Summary: Build FastAPI applications easily
Author: Guillaume Charbonnier
Author-email: gu.charbon@gmail.com
Requires-Python: >=3.8,<=3.10
Classifier: Programming Language :: Python :: 3
Classifier: Programming Language :: Python :: 3.8
Classifier: Programming Language :: Python :: 3.9
Classifier: Programming Language :: Python :: 3.10
Provides-Extra: dev
Provides-Extra: oidc
Provides-Extra: telemetry
Requires-Dist: PyJWT (>=2.3.0,<3.0.0); extra == "oidc"
Requires-Dist: PyYAML (>=6.0,<7.0)
Requires-Dist: black (>=22.3.0,<23.0.0); extra == "dev"
Requires-Dist: cryptography (>=36.0.2,<37.0.0); extra == "oidc"
Requires-Dist: fastapi (>=0.75.1,<0.76.0)
Requires-Dist: flake8 (>=4.0.1,<5.0.0); extra == "dev"
Requires-Dist: httpx (>=0.22.0,<0.23.0); extra == "oidc"
Requires-Dist: isort (>=5.10.1,<6.0.0); extra == "dev"
Requires-Dist: mypy (>=0.942,<0.943); extra == "dev"
Requires-Dist: nats-py (>=2.1.0,<3.0.0)
Requires-Dist: nkeys (>=0.1.0,<0.2.0)
Requires-Dist: opentelemetry-exporter-otlp-proto-grpc (>=1.10.0,<2.0.0)
Requires-Dist: opentelemetry-instrumentation-fastapi (>=0.29-beta.0,<0.29); extra == "telemetry"
Requires-Dist: opentelemetry-sdk (>=1.10.0,<2.0.0); extra == "telemetry"
Requires-Dist: prometheus-fastapi-instrumentator (>=5.7.1,<6.0.0); extra == "telemetry"
Requires-Dist: setuptools
Requires-Dist: structlog (>=21.5.0,<22.0.0)
Requires-Dist: types-PyYAML (>=6.0.7,<7.0.0); extra == "dev"
Requires-Dist: types-setuptools (>=57.4.12,<58.0.0); extra == "dev"
Requires-Dist: uvicorn (>=0.17.6,<0.18.0)
